pyszuru/__init__.py
pyszuru/api.py
pyszuru/pool.py
pyszuru/post.py
pyszuru/resource.py
pyszuru/search.py
pyszuru/tag.py
pyszuru-0.4.0.dist-info/LICENSE
pyszuru-0.4.0.dist-info/METADATA
pyszuru-0.4.0.dist-info/WHEEL
pyszuru-0.4.0.dist-info/top_level.txt
pyszuru-0.4.0.dist-info/RECORD
