Metadata-Version: 2.1
Name: pyszuru
Version: 0.4.0
Summary: Python interface for szurubooru
Home-page: https://github.com/sgsunder/python-szurubooru
Author: Shyam Sunder
Author-email: sgsunder1@gmail.com
License: UNKNOWN
Keywords: szurubooru,booru
Platform: UNKNOWN
Classifier: Programming Language :: Python :: 3
Classifier: License :: OSI Approved :: GNU General Public License v3 (GPLv3)
Classifier: Operating System :: OS Independent
Requires-Python: >=3.8
Requires-Dist: appdirs>=1.2.0
Requires-Dist: requests>=2.0.0
Requires-Dist: tqdm>=4.0.0
